src/__init__.py
src/awsdocs.py
awsdocs-0.0.8.dist-info/LICENSE
awsdocs-0.0.8.dist-info/METADATA
awsdocs-0.0.8.dist-info/WHEEL
awsdocs-0.0.8.dist-info/entry_points.txt
awsdocs-0.0.8.dist-info/top_level.txt
awsdocs-0.0.8.dist-info/RECORD
